{
  "id": "2026-0310-1",
  "guid": "scboy:2026:0310:BV1gBcdzZE7f",
  "title": "3月10号竞拍之王+智商杯+星际2RPG地图+杀戮尖塔2",
  "description": "prompt hash: 13dfd3, 04-28 13:09\n2026 0310-1\n(00:00:00) P2 闲聊天气很热，并问对方明天是否离开。\n(00:00:03) P2 预告晚上十点多会测试星际争霸相关的宝可梦/帕鲁玩法地图。\n(00:00:14) P2 回应弹幕说麦克风可能有问题，检查麦克风并讨论声音是否断断续续。\n(00:00:37) P2 继续讨论麦克风是否断断续续，确认自己这边听起来没有问题。\n(00:00:45) P2 有人离开去上厕所，并再次预告十点多测试星际帕鲁的一打一玩法，会叫MOMO和赤小兔参与。\n(00:00:59) P2 聊到该游戏正式版预计下个月推出，以及手游版适合碎片时间游玩。\n(00:01:18) P2 提到李培楠正在开电脑，马上加入。\n(00:01:21) P2 和李培楠沟通声音、当前玩的游戏、最后一天测试，以及把直播码发给他。\n(00:01:55) P2 结束当前竞拍游戏后，转去准备测试星际争霸MOD，讨论一打一带妹玩法、谁带谁、语音和采集星际画面、MOD是否要下载、不能打单人图和执政官模式、先用2V2地图测试效果以及OB安排。\n(00:04:16) P3 处理直播间弹幕冲突，驱赶乱喷观众，并讨论为什么不喷回去、直播间会不会被封。\n(00:04:45) P3 调试直播/语音音量，反复喂麦确认声音大小。\n(00:04:55) P3 因弹幕反馈声音问题暂停游戏，拿手机看弹幕并调整麦克风，确认爆麦问题改善。\n(00:05:39) P3 孙哥说自己平常低血压，被刚才的对局气到要去量血压，其他人让他量完回来。\n(00:06:00) P3 孙哥量出血压约120/84，众人调侃这是把低血压治好了，并继续拿带赤小兔会让人血压升高开玩笑。\n(00:06:57) P3 继续围绕血压数值、脉搏和是否算标准血压进行调侃。\n(00:07:18) P3 因为没有F10无法继续，转而聊到键盘F10键帽/键轴坏了被扣掉。\n(00:08:04) P3 讲述今天坐火车差点坐错去南昌的经历，包括站台两边火车、跟着别人上错车、差点晚上回不来直播。\n(00:10:11) P3 李培楠表示嗓子快喊哑了、明天有事，打完最后一把要早点休息。\n(00:10:28) P3 从星际转到约钱哥12点玩杀戮尖塔/爬塔，讨论游戏名、Steam购买下载、联机人数和多人mod安装，并指导孙哥等人解压、运行脚本、按选项安装模组。\n(00:16:08) P4 对局正式开始前的安装与准备：教孙哥、黄哥等运行游戏、安装多人/DPS mod、解锁角色、进房和选职业；期间处理麦克风炸音、聊炉石基础、昨天输出排名和谁能玩懂这类游戏等玩笑。\n(00:28:14) P4 有人在画/写东西时忘了“猪”字怎么写，其他人调侃字写错了。\n(00:28:24) P4 短暂偏题到给丁小涵画头像，并问头像好不好看。\n(00:28:31) P4 闲聊老虎加入他们后天天被骂、是否被霸凌，互相说谁素质差。\n(00:28:56) P4 围绕“睡一觉”的说法开玩笑并提到昨天也有类似桥段，随后有人说屏幕黑了，其他人怀疑是显示器插头或电源问题。\n(00:29:21) P4 暂停等人上厕所和处理肚子疼、买牛奶等情况；等待期间聊多人mod可支持的人数、是否能中途退出或继续、大家困了想睡、钱还没花，以及群里发的画。\n(00:35:31) P4 局后/收尾闲聊：有人要睡觉，讨论保存退出、明天是否继续；评价这个肉鸽游戏和战士流派；转聊拍卖游戏、宝可梦、明天CSL星际战队赛安排、组队和晚安收播。\n",
  "publishedAt": "2026-03-10T08:00:00+08:00",
  "seasonNumber": "2026",
  "episodeNumber": "0310-1",
  "audioUrl": "https://pub-335a48adb6074d2b944650a251c09eb2.r2.dev/episodes/2026/0310-BV1gBcdzZE7f-13dfd3.m4a",
  "audioBytes": 27721488,
  "audioType": "audio/mp4",
  "durationSeconds": 2405.0355,
  "source": {
    "outputDir": "output/2026/03-10-3月10号竞拍之王+智商杯+星际2RPG地图+杀戮尖塔2",
    "audioFileName": "BV1gBcdzZE7f.merge.offtopic.m4a",
    "shownotesFileName": "BV1gBcdzZE7f.shownotes.txt",
    "bvid": "BV1gBcdzZE7f",
    "objectKey": "episodes/2026/0310-BV1gBcdzZE7f-13dfd3.m4a"
  }
}
