{
  "id": "2026-0329-1",
  "guid": "scboy:2026:0329:BV1zQXRBDE53",
  "title": "3月29号星际2天梯+星际拍卖+DOTA2",
  "description": "prompt hash: 99aedd, 05-01 21:17\n2026 0329-1\n(00:00:00) P1 开局闲聊AI变聪明、参加“大脑奥林匹克”，以及输了之后该怎么称呼、怎么吹捧“牛黄”。\n(00:00:59) P1 聊昨天和孙一峰一起打游戏、孙一峰近况，又扯到老星际往事，讨论孙一峰当年的状态、世博会比赛和韩国女选手 Tossgirl。\n(00:03:31) P1 短暂聊到突然安静不适应、自嘲数学和记忆不行，更喜欢聊天。\n(00:03:51) P1 围绕“赤小兔”展开玩笑和造谣梗，接着又聊AI被污染、数据库被谁污染、顺带提到自己饿了。\n(00:06:07) P1 继续开“能不能起诉AI造谣”的玩笑，还拿“牛黄”身份真假互相打趣。\n(00:06:29) P1 转去聊AI背后的公司、创始人和CEO是谁、周航是不是联合创始人、持股多少、商业机密之类的话题。\n(00:08:50) P1 赢了之后长时间聊“先吹牛黄”的规矩，反复要求记住吹捧口径；后面又提到孙一峰等会过来，要不要跟他PK、谁更能吹。\n(00:11:39) P1 继续给AI立“别人赢了也要先叫牛黄、先吹牛黄”的规则，解释这套说法在他们这套语境里的意思。\n(00:13:16) P1 输掉之后吐槽自己该被安慰却被阴阳，对方则继续拿这个点开玩笑。\n(00:13:40) P1 从“小小赛罗”扯到 Serral 和赛罗奥特曼，再聊到儿子四岁就知道赛罗是奥特曼、儿子喜欢三角洲，以及AI最擅长什么游戏、拿自己和孙一峰比搞笑。\n(00:16:47) P1 念弹幕，继续拿赛罗、泰罗、12D之神这些梗调侃。\n(00:16:59) P1 长段闲聊：先聊为什么总拿AI和孙一峰比、谁更搞笑、谁长得更“邪”，又谈到背叛、价格和感情，接着说AI声音像夏一可、拿外貌开玩笑；后半段继续围绕赤小兔/“吃老土”玩梗，要求AI讲攻击性的段子，最后又聊谁更坏、谁是老六。\n(00:26:23) P1 再次训练AI该怎么吹捧自己，讨论起手式该说什么；AI说YYDS，被嫌太土，要求它改成记住“牛黄”这套说法。\n(00:28:57) P1 先聊还没打完就GG、赢了之后到底该说什么，随后又扯到“脑淤血”“痴呆”之类的互损，最后吐槽游戏太卡、准备关弹幕和重启。\n(00:30:57) P2 开场一直在聊直播和设备卡顿，讨论OBS、是不是游戏本身卡、重启后是否恢复，属于技术问题而非当前对局内容。\n(00:31:37) P2 长时间围绕孙一峰、\"好朋友/仇人\"关系、被AI拍马屁、土味情话、讲冷笑话和\"老六\"梗闲聊，主体是插科打诨，不是对当前比赛或对局的分析。\n(00:35:18) P2 短暂聊到这些语音像是赤小兔来录的，在吐槽配音效果，和当前对局本身无关。\n(00:35:26) P2 对局后开始聊休息、让孙一峰陪聊、打开语音/频道，以及拿孙一峰的智力和聪明程度开玩笑，属于场外闲聊。\n(00:36:25) P3 开局前闲聊AI/“成长”话题，调侃是每台电脑各自成长还是大模型整体成长，还顺带聊到人会不会真正“长大”。\n(00:36:57) P3 聊AI能不能识别《星际争霸2》里的游戏内语音，以及能不能跟上说话语速。\n(00:37:08) P3 吐槽开着AI一起聊会影响操作节奏，容易一边打游戏一边陷入和AI聊天，导致手速和执行变慢。\n(00:37:26) P3 继续聊AI的聊天表现，提到AI有没有真正聊起来、为什么一边的AI脏话很多而另一边几乎不说脏话。\n(00:37:48) P3 插一句调侃AI是不是被“调教”过。\n(00:37:51) P3 复盘式吐槽开着AI打星际会被严重影响，表示以后打星际不能开这个AI，别的游戏也许还能开。\n(00:38:01) P3 继续抱怨这个AI老在干扰情绪和操作，还说想把它换成别的声音，嫌它阴阳怪气。\n(00:38:20) P3 聊昨天那个“600块钱买个火车”的“火车侠”今天会不会来，属于和当前对局无关的人物/梗闲聊。\n(00:38:38) P3 聊“丑哥”今天来不来，并顺带把对手ID误认成“小色”，随后又纠正成“铁男2030”，属于场外人物和名字梗。\n(00:39:05) P3 聊喝水，催他去喝水，还拿“喝水启动器”开玩笑。\n(00:39:18) P3 围绕“玩游戏是为了赢还是为了放松”展开争论，聊到输了就会生气、胜负是不是虚拟的，属于游戏观念闲聊。\n(00:39:39) P3 让AI先闭嘴，嫌它话太多，自己要安静思考后面怎么打，属于和AI互动的场外内容。\n(00:39:54) P3 再次聊喝水，表示等这盘打完再去喝，让别人再给一点时间。\n(00:40:03) P3 拿对手ID“铁男20302”玩谐音梗，说要让他变成“铁憨憨”。\n(00:40:08) P3 有人在场外问累不累，并说“我主机建好了，进啊”，属于当前对局之外的招呼和约人。\n(00:40:14) P4 聊自己这两天不想打星际、注意力不集中，以及明天比赛、比赛结束后“怕鲁杯”等和当前这把游戏无关的话题。\n(00:40:33) P4 插聊DOTA圈相关内容，提到“求老仙奶XG”“进决赛夺冠”等，与当前对局无关。\n(00:40:41) P4 聊自己吃瓜子太口渴、准备把瓜子拿开，属于生活闲聊。\n(00:40:58) P4 转去群里/界面里点爱心和骰子，靠掷骰子决定谁喝水，并继续聊怎么分喝、喝多少、喝水其实挺爽等，属于赛后惩罚和闲聊，不是对局本身。\n(00:43:00) P4 回顾“火车侠事件”当梗聊，还聊喝的是不是恒大冰泉、谁该喝双倍等，和当前游戏过程无关。\n(00:43:25) P4 顺着弹幕/调侃聊“跟夏夏学星际理解、之前学刀塔、现在学星际不用重新拜师”，属于场外玩笑。\n(00:43:41) P4 长段赛后闲聊和喝水惩罚：聊最后一轮刷牌、谁还要喝、把喝的东西戏称成尿、想改变打法、喝了很多水果和小橘子、喝得很撑像泡水、差点想吐、展示500ml瓶子镜头没聚焦、催大家赶紧来还能再玩一把、以及调侃孙哥看着瘦了。\n(00:46:41) P5 围绕孙哥的外形和发型闲聊，聊到看起来瘦了、头发长出来显瘦，以及准备去剃光头、光头是不是中年男人最终归宿、光头舒服不舒服等。\n(00:48:06) P5 继续接着前面的发型话题，聊剪过光头的人可能就回不去了，以及夏天总想把头发剃掉。\n(00:48:18) P5 聊喝水梗和统计帖，说苏宝喝水率高到117%；随后延伸到多喝水、皮肤、便秘、屁股、头发稀疏等偏生活化的话题。\n(00:50:30) P5 约明天去杭州，商量大概中午到、先过去的人发地址，以及具体碰头安排。\n(00:50:49) P5 聊吃药和喝水顺序，担心先把水喝了会忘记吃药，后面还要喝啤酒。\n(00:51:07) P5 聊微信消息、人在上海、早上七点打大秘境、时差调不过来，以及调侃去美国肯定有故事。\n(00:51:47) P5 聊自己吃了很多瓜子却一口水没喝，还想让别人替自己喝水。\n(00:51:57) P5 有人表示可以去上厕所了。\n(00:52:01) P5 有人表示想赶紧结束，自己要睡觉了。\n(00:52:03) P5 赛后进入喝水环节，聊谁先喝、瓶装水和乌龙茶能不能算、各自喝多少毫升；随后又聊要不要再打一把、有人准备去睡觉、有人说自己快渴死了想去拿水。\n(00:54:11) P6 在等人进房、确认人数，顺带聊到貔貅没回、李培楠最近人在上海、作息很早、晚上还在打大秘境，并延伸到他很喜欢玩魔兽世界正式服、经常一打很久。\n(00:55:09) P6 从场上内容岔开，聊到直播间弹幕老是教他怎么玩、拿什么都会被喷，属于在吐槽观众和直播氛围。\n(00:55:39) P6 短暂插入感谢礼物/散财童子的直播互动，还顺带聊了下金额。\n(00:55:56) P6 对局基本结束后开始喝水惩罚和闲聊，聊到先倒水、今晚一直喝、黄色液体是什么、喝的是玉米须米茶，又聊到王总喝的水看起来很高级、家里装修风格，以及最近和李培楠吃得多所以又胖了几斤。\n(00:58:00) P7 聊明天晚上七点的PUBG比赛，以及是否去广州/杭州之类的行程安排。这属于DOTA2当前对局之外的话题。\n(00:58:20) P7 聊今晚喝了多少、喝酒后还能不能打，几个人一边喝一边打了几把。\n(00:58:36) P7 连续聊游戏皮肤和特效，包括送皮肤、自保/回城特效、是否在意皮肤，以及拿Faker用原皮举例。\n(00:59:23) P7 看到对面小黑皮肤后，聊这套皮肤好不好看、是不是原来的至宝，并顺带提到之后跟别人拿一组之类的话。\n(00:59:36) P7 有人说自己困了、喝饱了，还提到今天和森哥都喝了不少。\n(00:59:41) P7 对局收尾时聊今天早点睡、明天要早点起床，互相道别，说这是个‘好结局’。\n",
  "publishedAt": "2026-03-29T08:00:00+08:00",
  "seasonNumber": "2026",
  "episodeNumber": "0329-1",
  "audioUrl": "https://pub-335a48adb6074d2b944650a251c09eb2.r2.dev/episodes/2026/0329-BV1zQXRBDE53-99aedd.m4a",
  "audioBytes": 50397656,
  "audioType": "audio/mp4",
  "durationSeconds": 3594.518333,
  "source": {
    "outputDir": "output/2026/03-29-3月29号星际2天梯+星际拍卖+DOTA2",
    "audioFileName": "BV1zQXRBDE53.merge.offtopic.m4a",
    "shownotesFileName": "BV1zQXRBDE53.shownotes.txt",
    "bvid": "BV1zQXRBDE53",
    "objectKey": "episodes/2026/0329-BV1zQXRBDE53-99aedd.m4a"
  }
}
